particleseg3d/__init__.py
particleseg3d/_tests/__init__.py
particleseg3d/conversion/__init__.py
particleseg3d/conversion/nifti2tiff.py
particleseg3d/conversion/nifti2zarr.py
particleseg3d/conversion/tiff2nifti.py
particleseg3d/conversion/tiff2zarr.py
particleseg3d/conversion/zarr2tiff.py
particleseg3d/inference/__init__.py
particleseg3d/inference/aggregator.py
particleseg3d/inference/border_core2instance.py
particleseg3d/inference/inference.py
particleseg3d/inference/model_nnunet.py
particleseg3d/inference/sampler.py
particleseg3d/train/__init__.py
particleseg3d/train/instance2border_core.py
particleseg3d/train/preprocess.py
particleseg3d/utils/__init__.py
particleseg3d/utils/change_spacing.py
particleseg3d/utils/nnunet_utils.py
particleseg3d/utils/utils.py
ParticleSeg3D-0.2.16.dist-info/LICENSE
ParticleSeg3D-0.2.16.dist-info/METADATA
ParticleSeg3D-0.2.16.dist-info/WHEEL
ParticleSeg3D-0.2.16.dist-info/entry_points.txt
ParticleSeg3D-0.2.16.dist-info/top_level.txt
ParticleSeg3D-0.2.16.dist-info/RECORD
