Metadata-Version: 2.1
Name: ParticleSeg3D
Version: 0.2.16
Summary: Scalable, out-of-the box segmentation of individual particles from mineral samples acquired with micro CT
Author: Karol Gotkowski
Author-email: karol.gotkowski@dkfz.de
License: Apache-2.0
Classifier: Development Status :: 2 - Pre-Alpha
Classifier: Intended Audience :: Developers
Classifier: License :: OSI Approved :: Apache Software License
Classifier: Operating System :: OS Independent
Classifier: Programming Language :: Python
Classifier: Programming Language :: Python :: 3
Classifier: Programming Language :: Python :: 3 :: Only
Classifier: Programming Language :: Python :: 3.8
Classifier: Programming Language :: Python :: 3.9
Classifier: Programming Language :: Python :: 3.10
Classifier: Topic :: Scientific/Engineering :: Image Processing
Requires-Python: >=3.8
License-File: LICENSE
Requires-Dist: numpy
Requires-Dist: tqdm
Requires-Dist: SimpleITK
Requires-Dist: zarr
Requires-Dist: GeodisTK
Requires-Dist: connected-components-3d
Requires-Dist: numpy-indexed
Requires-Dist: scikit-image
Requires-Dist: acvl-utils
Requires-Dist: natsort
Requires-Dist: pytorch-lightning <=1.9.5
Provides-Extra: testing
Requires-Dist: tox ; extra == 'testing'
Requires-Dist: pytest ; extra == 'testing'
Requires-Dist: pytest-cov ; extra == 'testing'
